PyCQP_interface.py
cwb_python-0.2.2.dist-info/RECORD
cwb_python-0.2.2.dist-info/WHEEL
cwb_python-0.2.2.dist-info/METADATA
cwb_python-0.2.2.dist-info/metadata.json
cwb_python-0.2.2.dist-info/DESCRIPTION.rst
cwb_python-0.2.2.dist-info/top_level.txt
cwb_python-0.2.2.dist-info/entry_points.txt
CWB/CL.so
CWB/__init__.py
CWB/.libs/libpcre-d0db370e.so.0.0.1
CWB/tools/cqp2vocab.py
CWB/tools/__init__.py
CWB/tools/make_bitext.py
CWB/tools/cqp2conll.py
