Metadata-Version: 2.0
Name: cwb-python
Version: 0.2.2
Summary: CQP and CL interfaces for Python
Home-page: https://bitbucket.org/yannick/cwb-python
Author: Yannick Versley / Jorg Asmussen
Author-email: yversley@googlemail.com
License: UNKNOWN
Platform: UNKNOWN
Requires-Dist: cython (>=0.19)
Requires-Dist: setuptools (>=17)
Requires-Dist: six
